render_engine_rss/__init__.py
render_engine_rss/collection.py
render_engine_rss/parsers.py
render_engine_rss/.vscode/settings.json
render_engine_rss/__pycache__/__init__.cpython-311.pyc
render_engine_rss/__pycache__/collection.cpython-311.pyc
render_engine_rss/__pycache__/parsers.cpython-311.pyc
render_engine_rss-2023.10.1.dist-info/METADATA
render_engine_rss-2023.10.1.dist-info/WHEEL
render_engine_rss-2023.10.1.dist-info/top_level.txt
render_engine_rss-2023.10.1.dist-info/RECORD
