Metadata-Version: 2.1
Name: render-engine-rss
Version: 2023.10.1
Summary: RSS Parser and Collection for Render Engine
Project-URL: homepage, https://github.com/kjaymiller/render_engine_json/
Project-URL: repository, https://github.com/kjaymiller/render_engine_json/
Requires-Dist: render-engine >=2023.3.1b14
Requires-Dist: feedparser
Provides-Extra: dev
Requires-Dist: pytest ; extra == 'dev'
Requires-Dist: pytest-mock ; extra == 'dev'
